{
	"description": "项目配置文件",
	"packOptions": {
		"ignore": []
	},
	"setting": {
		"urlCheck": false,
		"es6": true,
		"postcss": true,
		"minified": true,
		"newFeature": true,
		"autoAudits": false
	},
	"compileType": "miniprogram",
	"libVersion": "2.6.2",
	"appid": "wx4024f753ea58edaf",
	"projectname": "idoctor",
	"debugOptions": {
		"hidedInDevtools": []
	},
	"isGameTourist": false,
	"condition": {
		"search": {
			"current": -1,
			"list": []
		},
		"conversation": {
			"current": -1,
			"list": []
		},
		"plugin": {
			"current": -1,
			"list": []
		},
		"game": {
			"currentL": -1,
			"list": []
		},
		"miniprogram": {
			"current": 1,
			"list": [
				{
					"id": -1,
					"name": "search",
					"pathName": "pages/search/search",
					"query": "",
					"scene": null
				},
				{
					"id": -1,
					"name": "test",
					"pathName": "pages/index/index",
					"query": "",
					"scene": null
				}
			]
		}
	}
}